pylecular/__init__.py
pylecular/broker.py
pylecular/cli.py
pylecular/context.py
pylecular/decorators.py
pylecular/discoverer.py
pylecular/lifecycle.py
pylecular/logger.py
pylecular/middleware.py
pylecular/node.py
pylecular/packet.py
pylecular/registry.py
pylecular/service.py
pylecular/settings.py
pylecular/transit.py
pylecular/validator.py
pylecular/transporter/base.py
pylecular/transporter/nats.py
pylecular-0.1.13.dist-info/METADATA
pylecular-0.1.13.dist-info/WHEEL
pylecular-0.1.13.dist-info/entry_points.txt
pylecular-0.1.13.dist-info/licenses/LICENSE
pylecular-0.1.13.dist-info/RECORD
