Metadata-Version: 2.4
Name: pylecular
Version: 0.1.13
Summary: Python Moleculer Library
Author-email: Alvaro Inckot <alvaroinckot@gmail.com>
License-File: LICENSE
Requires-Python: >=3.8
Requires-Dist: nats-py>=2.10.0
Requires-Dist: psutil>=7.0.0
Requires-Dist: structlog>=25.3.0
Provides-Extra: dev
Requires-Dist: mypy>=1.5.1; extra == 'dev'
Requires-Dist: pre-commit>=3.5.0; extra == 'dev'
Requires-Dist: ruff>=0.1.9; extra == 'dev'
Provides-Extra: test
Requires-Dist: pytest-asyncio>=0.26.0; extra == 'test'
Requires-Dist: pytest>=8.3.5; extra == 'test'
